[
  {
    "name": "minScore",
    "expected": 0.9,
    "actual": 0,
    "values": [
      0,
      0,
      0
    ],
    "operator": ">=",
    "passed": false,
    "auditId": "bootup-time",
    "level": "warn",
    "url": "http://localhost:3000/",
    "auditTitle": "JavaScript execution time",
    "auditDocumentationLink": "https://developer.chrome.com/docs/lighthouse/performance/bootup-time/"
  },
  {
    "name": "minScore",
    "expected": 0.9,
    "actual": 0,
    "values": [
      0,
      0,
      0
    ],
    "operator": ">=",
    "passed": false,
    "auditId": "csp-xss",
    "level": "error",
    "url": "http://localhost:3000/",
    "auditTitle": "Ensure CSP is effective against XSS attacks",
    "auditDocumentationLink": "https://developer.chrome.com/docs/lighthouse/best-practices/csp-xss/"
  },
  {
    "name": "minScore",
    "expected": 0.9,
    "actual": 0,
    "values": [
      0,
      0,
      0
    ],
    "operator": ">=",
    "passed": false,
    "auditId": "dom-size",
    "level": "warn",
    "url": "http://localhost:3000/",
    "auditTitle": "Avoids an excessive DOM size",
    "auditDocumentationLink": "https://developers.google.com/web/fundamentals/performance/rendering/reduce-the-scope-and-complexity-of-style-calculations"
  },
  {
    "name": "minScore",
    "expected": 0.9,
    "actual": 0,
    "values": [
      0,
      0,
      0
    ],
    "operator": ">=",
    "passed": false,
    "auditId": "installable-manifest",
    "level": "error",
    "url": "http://localhost:3000/",
    "auditTitle": "Web app manifest or service worker do not meet the installability requirements",
    "auditDocumentationLink": "https://developer.chrome.com/docs/lighthouse/pwa/installable-manifest/"
  },
  {
    "name": "minScore",
    "expected": 0.9,
    "actual": 0,
    "values": [
      0,
      0,
      0
    ],
    "operator": ">=",
    "passed": false,
    "auditId": "mainthread-work-breakdown",
    "level": "warn",
    "url": "http://localhost:3000/",
    "auditTitle": "Minimizes main-thread work",
    "auditDocumentationLink": "https://developer.chrome.com/docs/lighthouse/performance/mainthread-work-breakdown/"
  },
  {
    "name": "minScore",
    "expected": 0.9,
    "actual": 0,
    "values": [
      0,
      0,
      0
    ],
    "operator": ">=",
    "passed": false,
    "auditId": "maskable-icon",
    "level": "error",
    "url": "http://localhost:3000/",
    "auditTitle": "Manifest doesn't have a maskable icon",
    "auditDocumentationLink": "https://developer.chrome.com/docs/lighthouse/pwa/maskable-icon-audit/"
  },
  {
    "name": "maxLength",
    "expected": 0,
    "actual": 2,
    "values": [
      2,
      2,
      2
    ],
    "operator": "<=",
    "passed": false,
    "auditId": "render-blocking-resources",
    "level": "warn",
    "url": "http://localhost:3000/",
    "auditTitle": "Eliminate render-blocking resources",
    "auditDocumentationLink": "https://developer.chrome.com/docs/lighthouse/performance/render-blocking-resources/"
  },
  {
    "name": "minScore",
    "expected": 0.9,
    "actual": 0,
    "values": [
      0,
      0,
      0
    ],
    "operator": ">=",
    "passed": false,
    "auditId": "server-response-time",
    "level": "warn",
    "url": "http://localhost:3000/",
    "auditTitle": "Initial server response time was short",
    "auditDocumentationLink": "https://developer.chrome.com/docs/lighthouse/performance/time-to-first-byte/"
  },
  {
    "name": "minScore",
    "expected": 0.9,
    "actual": 0,
    "values": [
      0,
      0,
      0
    ],
    "operator": ">=",
    "passed": false,
    "auditId": "splash-screen",
    "level": "error",
    "url": "http://localhost:3000/",
    "auditTitle": "Is not configured for a custom splash screen",
    "auditDocumentationLink": "https://developer.chrome.com/docs/lighthouse/pwa/splash-screen/"
  },
  {
    "name": "minScore",
    "expected": 0.9,
    "actual": 0,
    "values": [
      0,
      0,
      0
    ],
    "operator": ">=",
    "passed": false,
    "auditId": "themed-omnibox",
    "level": "error",
    "url": "http://localhost:3000/",
    "auditTitle": "Does not set a theme color for the address bar.",
    "auditDocumentationLink": "https://developer.chrome.com/docs/lighthouse/pwa/themed-omnibox/"
  },
  {
    "name": "minScore",
    "expected": 0.9,
    "actual": 0,
    "values": [
      0,
      0,
      0
    ],
    "operator": ">=",
    "passed": false,
    "auditId": "total-byte-weight",
    "level": "error",
    "url": "http://localhost:3000/",
    "auditTitle": "Avoids enormous network payloads",
    "auditDocumentationLink": "https://developer.chrome.com/docs/lighthouse/performance/total-byte-weight/"
  },
  {
    "name": "maxLength",
    "expected": 0,
    "actual": 1,
    "values": [
      1,
      1,
      1
    ],
    "operator": "<=",
    "passed": false,
    "auditId": "unused-javascript",
    "level": "error",
    "url": "http://localhost:3000/",
    "auditTitle": "Reduce unused JavaScript",
    "auditDocumentationLink": "https://developer.chrome.com/docs/lighthouse/performance/unused-javascript/"
  }
]